ciuy/__init__.py
ciuy/command_line.py
ciuy-1.0.0.dist-info/LICENSE
ciuy-1.0.0.dist-info/METADATA
ciuy-1.0.0.dist-info/WHEEL
ciuy-1.0.0.dist-info/entry_points.txt
ciuy-1.0.0.dist-info/top_level.txt
ciuy-1.0.0.dist-info/zip-safe
ciuy-1.0.0.dist-info/RECORD
