Metadata-Version: 2.1
Name: ciuy
Version: 1.0.0
Summary: Python package for validating Uruguayan identity document numbers.
Home-page: https://github.com/ismaelpadilla/ciuy_py
Author: Ismael Padilla
Author-email: padillaismael92@gmail.com
License: MIT
Project-URL: Documentation, https://ciuy.readthedocs.io/
Keywords: Uruguay,dni,id,eid,validation,cédula,cédula uruguaya
Platform: UNKNOWN
Classifier: Development Status :: 5 - Production/Stable
Classifier: License :: OSI Approved :: MIT License
Classifier: Operating System :: OS Independent
Classifier: Programming Language :: Python :: 3
Classifier: Programming Language :: Python :: 3.4
Classifier: Programming Language :: Python :: 3.5
Classifier: Programming Language :: Python :: 3.6
Classifier: Programming Language :: Python :: 3.7
Classifier: Programming Language :: Python :: 3.8
Requires-Python: >=3.4
